cellcanvas/__init__.py
cellcanvas/_version.py
cellcanvas/_widget.py
cellcanvas/app.py
cellcanvas/constants.py
cellcanvas/napari.yaml
cellcanvas/utils.py
cellcanvas/_app/__init__.py
cellcanvas/_app/main_app.py
cellcanvas/_tests/__init__.py
cellcanvas/_tests/test_widget.py
cellcanvas/geometry/__init__.py
cellcanvas/geometry/surforama.py
cellcanvas/instance/__init__.py
cellcanvas/instance/bounding_box_utils.py
cellcanvas/instance/fill.py
cellcanvas/instance/label_smoothing.py
cellcanvas/instance/mesh.py
cellcanvas/instance/paint.py
cellcanvas/instance/segment_manager.py
cellcanvas/instance/_qt/__init__.py
cellcanvas/instance/_qt/qt_morphological_operations.py
cellcanvas/instance/_qt/qt_segment_manager.py
cellcanvas/instance/_tests/__init__.py
cellcanvas/instance/_tests/test_segment_manager.py
cellcanvas/semantic/__init__.py
cellcanvas/semantic/embedding_paint.py
cellcanvas-0.0.1.dist-info/LICENSE
cellcanvas-0.0.1.dist-info/METADATA
cellcanvas-0.0.1.dist-info/WHEEL
cellcanvas-0.0.1.dist-info/entry_points.txt
cellcanvas-0.0.1.dist-info/top_level.txt
cellcanvas-0.0.1.dist-info/RECORD
